eluvina_automl.py
start_automl.py
simplified_automl-0.0.4.dist-info/METADATA
simplified_automl-0.0.4.dist-info/WHEEL
simplified_automl-0.0.4.dist-info/entry_points.txt
simplified_automl-0.0.4.dist-info/license.key
simplified_automl-0.0.4.dist-info/license.py
simplified_automl-0.0.4.dist-info/top_level.txt
simplified_automl-0.0.4.dist-info/RECORD
